aragog/__init__.py
aragog/cfg/__init__.py
aragog/cfg/abe_liquid.cfg
aragog/cfg/abe_mixed.cfg
aragog/cfg/abe_mixed_init.cfg
aragog/cfg/abe_mixed_lookup.cfg
aragog/cfg/abe_solid.cfg
aragog/cli.py
aragog/core.py
aragog/data.py
aragog/interfaces.py
aragog/mesh.py
aragog/output.py
aragog/parser.py
aragog/phase.py
aragog/solver.py
aragog/utilities.py
aragog/notebooks/__init__.py
aragog-0.2.9a0.dist-info/METADATA
aragog-0.2.9a0.dist-info/WHEEL
aragog-0.2.9a0.dist-info/entry_points.txt
aragog-0.2.9a0.dist-info/licenses/LICENSE
aragog-0.2.9a0.dist-info/RECORD
