Metadata-Version: 2.4
Name: aragog
Version: 0.2.9a0
Summary: 1-D interior dynamics of rocky mantles that are solid, liquid, or mixed phase
License: GPL-3.0-or-later
License-File: LICENSE
Author: Dan J Bower
Author-email: djbower@users.noreply.github.com
Requires-Python: >=3.10
Classifier: License :: OSI Approved :: GNU General Public License v3 or later (GPLv3+)
Classifier: Programming Language :: Python :: 3
Classifier: Programming Language :: Python :: 3.10
Classifier: Programming Language :: Python :: 3.11
Classifier: Programming Language :: Python :: 3.12
Classifier: Programming Language :: Python :: 3.13
Classifier: Programming Language :: Python :: 3.14
Provides-Extra: docs
Requires-Dist: click (>=8.1.3,<9.0.0)
Requires-Dist: matplotlib (>=3.8.3,<4.0.0)
Requires-Dist: netCDF4 (>=1.7.0,<2.0.0)
Requires-Dist: numpy (>=2.0.0)
Requires-Dist: osfclient (>=0.0.5,<0.0.6)
Requires-Dist: platformdirs (>=3.10.0,<4.0.0)
Requires-Dist: scipy (>=1.12.0,<2.0.0)
Requires-Dist: setuptools (==70.0.0) ; extra == "docs"
Requires-Dist: sphinx (==7.2.6) ; extra == "docs"
Requires-Dist: sphinx-rtd-theme (==2.0.0) ; extra == "docs"
Requires-Dist: sphinxcontrib-bibtex (==2.6.3) ; extra == "docs"
Requires-Dist: thermochem (>=0.8.2,<0.9.0)
Requires-Dist: typed-configparser (>=1.1.0,<2.0.0)
Requires-Dist: typing-extensions (>=4.10.0,<5.0.0)
Requires-Dist: zenodo_get (>=1.6.0)
